setup.py
char_rbm/__init__.py
char_rbm/codec.py
char_rbm/sampling.py
char_rbm/simple.py
char_rbm/utils.py
char_rbm.egg-info/PKG-INFO
char_rbm.egg-info/SOURCES.txt
char_rbm.egg-info/dependency_links.txt
char_rbm.egg-info/requires.txt
char_rbm.egg-info/top_level.txt