Metadata-Version: 1.0
Name: char-rbm
Version: 0.1.1
Summary: simple interface to train and sample char-rbms
Home-page: UNKNOWN
Author: jarbasai
Author-email: jarbasai@mailfence.com
License: UNKNOWN
Platform: UNKNOWN
